Metadata-Version: 2.1
Name: html-report-generator
Version: 0.0.1
Summary: Report generator for html reports
Home-page: UNKNOWN
Author: numerous - Tobias Skov Reipuert, Tobias Dokkedal Elmøe, Lasse Nyberg Thomsen, Ósk Björnsdottir
Author-email: report-generator@numerous.com
License: O-BSD-3
Platform: UNKNOWN
Classifier: Programming Language :: Python :: 3
Classifier: License :: OSI Approved :: BSD License
Classifier: Operating System :: OS Independent
Requires-Python: >=3.9
License-File: LICENSE
Requires-Dist: jinja2 (>=3.0.0)
Requires-Dist: plotly (>=5.8.2)
Requires-Dist: pytest (>=7.1.2)
Requires-Dist: beautifulsoup4 (>=4.11.1)
Requires-Dist: pandas
